earthkit/maps/__init__.py
earthkit/maps/data.py
earthkit/maps/definitions.py
earthkit/maps/inputs.py
earthkit/maps/quickplot.py
earthkit/maps/schemas.py
earthkit/maps/utils.py
earthkit/maps/version.py
earthkit/maps/charts/__init__.py
earthkit/maps/charts/layers.py
earthkit/maps/charts/layouts.py
earthkit/maps/charts/subplots.py
earthkit/maps/data/domains.yaml
earthkit/maps/data/schemas/bom.yaml
earthkit/maps/data/schemas/default.yaml
earthkit/maps/data/schemas/ecmwf.yaml
earthkit/maps/data/static/fonts/Lato/Lato-Black.ttf
earthkit/maps/data/static/fonts/Lato/Lato-BlackItalic.ttf
earthkit/maps/data/static/fonts/Lato/Lato-Bold.ttf
earthkit/maps/data/static/fonts/Lato/Lato-BoldItalic.ttf
earthkit/maps/data/static/fonts/Lato/Lato-Italic.ttf
earthkit/maps/data/static/fonts/Lato/Lato-Light.ttf
earthkit/maps/data/static/fonts/Lato/Lato-LightItalic.ttf
earthkit/maps/data/static/fonts/Lato/Lato-Regular.ttf
earthkit/maps/data/static/fonts/Lato/Lato-Thin.ttf
earthkit/maps/data/static/fonts/Lato/Lato-ThinItalic.ttf
earthkit/maps/data/static/fonts/OpenSans/OFL.txt
earthkit/maps/data/static/fonts/OpenSans/OpenSans-Bold.ttf
earthkit/maps/data/static/fonts/OpenSans/OpenSans-BoldItalic.ttf
earthkit/maps/data/static/fonts/OpenSans/OpenSans-ExtraBold.ttf
earthkit/maps/data/static/fonts/OpenSans/OpenSans-ExtraBoldItalic.ttf
earthkit/maps/data/static/fonts/OpenSans/OpenSans-Italic.ttf
earthkit/maps/data/static/fonts/OpenSans/OpenSans-Light.ttf
earthkit/maps/data/static/fonts/OpenSans/OpenSans-LightItalic.ttf
earthkit/maps/data/static/fonts/OpenSans/OpenSans-Medium.ttf
earthkit/maps/data/static/fonts/OpenSans/OpenSans-MediumItalic.ttf
earthkit/maps/data/static/fonts/OpenSans/OpenSans-Regular.ttf
earthkit/maps/data/static/fonts/OpenSans/OpenSans-SemiBold.ttf
earthkit/maps/data/static/fonts/OpenSans/OpenSans-SemiBoldItalic.ttf
earthkit/maps/data/static/images/logos/ecmwf.png
earthkit/maps/data/styles/2m-temperature.yaml
earthkit/maps/data/styles/mean-sea-level-pressure.yaml
earthkit_maps-0.18.dist-info/LICENSE
earthkit_maps-0.18.dist-info/METADATA
earthkit_maps-0.18.dist-info/WHEEL
earthkit_maps-0.18.dist-info/top_level.txt
earthkit_maps-0.18.dist-info/RECORD
