Metadata-Version: 2.1
Name: earthkit-maps
Version: 0.18
Summary: Geospatial visualisation tools and templates
License: Apache License 2.0
Classifier: Development Status :: 2 - Pre-Alpha
Classifier: Intended Audience :: Science/Research
Classifier: License :: OSI Approved :: Apache Software License
Classifier: Operating System :: OS Independent
Classifier: Programming Language :: Python
Classifier: Programming Language :: Python :: 3
Classifier: Programming Language :: Python :: 3.8
Classifier: Programming Language :: Python :: 3.9
Classifier: Programming Language :: Python :: 3.10
Classifier: Programming Language :: Python :: 3.11
Classifier: Topic :: Scientific/Engineering
License-File: LICENSE
Requires-Dist: earthkit-data
Requires-Dist: cartopy >=0.22.0
Requires-Dist: matplotlib
Requires-Dist: pyyaml
Requires-Dist: numpy
Requires-Dist: adjustText
